open_soup_rating/__init__.py
open_soup_rating/cli.py
open_soup_rating/components/__init__.py
open_soup_rating/components/adra.py
open_soup_rating/components/apr.py
open_soup_rating/components/death_contrib.py
open_soup_rating/components/kill_contrib.py
open_soup_rating/core/__init__.py
open_soup_rating/core/component_registry.py
open_soup_rating/core/rating_calculator.py
open_soup_rating/data/__init__.py
open_soup_rating/data/loader.py
open_soup_rating/utils/__init__.py
open_soup_rating/utils/config.py
open_soup_rating/utils/validation.py
opensouprating-1.1.1.dist-info/METADATA
opensouprating-1.1.1.dist-info/WHEEL
opensouprating-1.1.1.dist-info/entry_points.txt
opensouprating-1.1.1.dist-info/top_level.txt
opensouprating-1.1.1.dist-info/RECORD
