Metadata-Version: 2.4
Name: OpenSoupRating
Version: 1.1.1
Summary: A comprehensive, open-source rating system for Valorant player performance analysis
Author-email: Zach Lewis <your.email@example.com>
License-Expression: AGPL-3.0-or-later
Project-URL: Homepage, https://github.com/zachlewis/OpenSoupRating
Project-URL: Repository, https://github.com/zachlewis/OpenSoupRating
Project-URL: Issues, https://github.com/zachlewis/OpenSoupRating/issues
Project-URL: Documentation, https://github.com/zachlewis/OpenSoupRating#readme
Keywords: valorant,esports,rating,performance,analysis,gaming
Classifier: Development Status :: 4 - Beta
Classifier: Intended Audience :: Developers
Classifier: Intended Audience :: Science/Research
Classifier: Operating System :: OS Independent
Classifier: Programming Language :: Python :: 3
Classifier: Programming Language :: Python :: 3.9
Classifier: Programming Language :: Python :: 3.10
Classifier: Programming Language :: Python :: 3.11
Classifier: Programming Language :: Python :: 3.12
Classifier: Topic :: Games/Entertainment
Classifier: Topic :: Scientific/Engineering :: Information Analysis
Requires-Python: >=3.9
Provides-Extra: dev
Requires-Dist: pytest>=7.0; extra == "dev"
Requires-Dist: pytest-cov; extra == "dev"
Requires-Dist: black; extra == "dev"
Requires-Dist: flake8; extra == "dev"
Requires-Dist: mypy; extra == "dev"
Requires-Dist: pre-commit; extra == "dev"
Provides-Extra: full
